slang/__init__.py
slang/__main__.py
slang/cli.py
trade_slang-1.0.0.dist-info/LICENSE
trade_slang-1.0.0.dist-info/METADATA
trade_slang-1.0.0.dist-info/WHEEL
trade_slang-1.0.0.dist-info/entry_points.txt
trade_slang-1.0.0.dist-info/RECORD
