Metadata-Version: 2.1
Name: trade-slang
Version: 1.0.0
Summary: 
Author: Rodion Gudz
Author-email: rodion@gudz.ml
Requires-Python: >=3.10,<4.0
Classifier: Programming Language :: Python :: 3
Classifier: Programming Language :: Python :: 3.10
Classifier: Programming Language :: Python :: 3.11
Requires-Dist: requests (>=2.30.0,<3.0.0)
Requires-Dist: rich-click (>=1.6.1,<2.0.0)
